tp_analyzer/__init__.py
tp_analyzer/hello.py
tp_analyzer/identify_tps.py
tp_analyzer/us_covid_stats.py
tp_analyzer/utils.py
tp_analyzer/data/us-states.csv
tp_analyzer-0.0.4.dist-info/LICENSE
tp_analyzer-0.0.4.dist-info/METADATA
tp_analyzer-0.0.4.dist-info/WHEEL
tp_analyzer-0.0.4.dist-info/top_level.txt
tp_analyzer-0.0.4.dist-info/RECORD
