Metadata-Version: 2.1
Name: tp-analyzer
Version: 0.0.4
Summary: A package to identify turning points in time series data
Home-page: https://github.com/jarrahl/tp-analyzer
Author: Nick James, Jarrah Lacko and Max Menzies
Author-email: jarrah@lacko.com.au
License: MIT License
Keywords: change point detection,turning points,time series
Platform: UNKNOWN
Classifier: Programming Language :: Python :: 3
Classifier: Operating System :: OS Independent
Classifier: Topic :: Scientific/Engineering :: Mathematics
Classifier: Intended Audience :: Science/Research
Classifier: License :: OSI Approved :: MIT License
Requires-Python: >=3
Requires-Dist: sortedcontainers
Requires-Dist: numpy
Requires-Dist: scipy
Requires-Dist: matplotlib
